kerochan/__init__.py
kerochan/backup.py
kerochan/errors.py
kerochan/import/__init__.py
kerochan/import/__main__.py
kerochan/importing.py
kerochan/sources.py
kerochan/structs.py
kerochan-0.1.0.dist-info/entry_points.txt
kerochan-0.1.0.dist-info/WHEEL
kerochan-0.1.0.dist-info/METADATA
kerochan-0.1.0.dist-info/RECORD
