Metadata-Version: 2.1
Name: kerochan
Version: 0.1.0
Summary: Kero-chan is a tool to help you collect your pictures from your camera
License: WTFPL
Author: Rémy Sanchez
Author-email: remy.sanchez@hyperthese.net
Requires-Python: >=3.8,<4.0
Classifier: License :: Other/Proprietary License
Classifier: Programming Language :: Python :: 3
Classifier: Programming Language :: Python :: 3.8
Requires-Dist: inquirer (>=2.7.0,<3.0.0)
Requires-Dist: parse (>=1.18.0,<2.0.0)
Requires-Dist: psutil (>=5.8.0,<6.0.0)
Requires-Dist: tqdm (>=4.55.1,<5.0.0)
